annet/__init__.py
annet/annet.py
annet/argparse.py
annet/bgp_models.py
annet/cli.py
annet/cli_args.py
annet/connectors.py
annet/deploy.py
annet/deploy_ui.py
annet/diff.py
annet/filtering.py
annet/gen.py
annet/hardware.py
annet/implicit.py
annet/lib.py
annet/output.py
annet/parallel.py
annet/patching.py
annet/reference.py
annet/storage.py
annet/text_term_format.py
annet/tracing.py
annet/types.py
annet/adapters/__init__.py
annet/adapters/fetchers/__init__.py
annet/adapters/fetchers/stub/__init__.py
annet/adapters/fetchers/stub/fetcher.py
annet/adapters/file/__init__.py
annet/adapters/file/provider.py
annet/adapters/netbox/__init__.py
annet/adapters/netbox/provider.py
annet/adapters/netbox/common/__init__.py
annet/adapters/netbox/common/adapter.py
annet/adapters/netbox/common/client.py
annet/adapters/netbox/common/manufacturer.py
annet/adapters/netbox/common/models.py
annet/adapters/netbox/common/query.py
annet/adapters/netbox/common/status_client.py
annet/adapters/netbox/common/storage_base.py
annet/adapters/netbox/common/storage_opts.py
annet/adapters/netbox/v24/__init__.py
annet/adapters/netbox/v24/models.py
annet/adapters/netbox/v24/storage.py
annet/adapters/netbox/v37/__init__.py
annet/adapters/netbox/v37/models.py
annet/adapters/netbox/v37/storage.py
annet/adapters/netbox/v41/__init__.py
annet/adapters/netbox/v41/models.py
annet/adapters/netbox/v41/storage.py
annet/adapters/netbox/v42/__init__.py
annet/adapters/netbox/v42/models.py
annet/adapters/netbox/v42/storage.py
annet/annlib/__init__.py
annet/annlib/command.py
annet/annlib/diff.py
annet/annlib/errors.py
annet/annlib/filter_acl.py
annet/annlib/jsontools.py
annet/annlib/lib.py
annet/annlib/output.py
annet/annlib/patching.py
annet/annlib/types.py
annet/annlib/netdev/__init__.py
annet/annlib/netdev/db.py
annet/annlib/netdev/devdb/__init__.py
annet/annlib/netdev/devdb/data/devdb.json
annet/annlib/netdev/views/__init__.py
annet/annlib/netdev/views/dump.py
annet/annlib/netdev/views/hardware.py
annet-3.22.6.dist-info/licenses/AUTHORS
annet-3.22.6.dist-info/licenses/LICENSE
annet-3.22.6.dist-info/METADATA
annet-3.22.6.dist-info/WHEEL
annet-3.22.6.dist-info/entry_points.txt
annet-3.22.6.dist-info/top_level.txt
annet-3.22.6.dist-info/RECORD
